inpainting_metrics/__init__.py
inpainting_metrics/challenge_metrics_2023.py
inpainting_metrics-0.0.1.dist-info/LICENSE
inpainting_metrics-0.0.1.dist-info/WHEEL
inpainting_metrics-0.0.1.dist-info/METADATA
inpainting_metrics-0.0.1.dist-info/RECORD
