Metadata-Version: 2.1
Name: inpainting-metrics
Version: 0.0.1
Summary: TODO.
License: AGPL-3.0
Author: Florian Kofler
Author-email: florian.kofler@tum.de
Requires-Python: >=3.6
Classifier: License :: OSI Approved :: GNU Affero General Public License v3
Classifier: Programming Language :: Python :: 3
Classifier: Programming Language :: Python :: 3.10
Classifier: Programming Language :: Python :: 3.6
Classifier: Programming Language :: Python :: 3.7
Classifier: Programming Language :: Python :: 3.8
Classifier: Programming Language :: Python :: 3.9
Requires-Dist: nibabel (>3.0)
Requires-Dist: numpy (>=1.25,<2.0)
Requires-Dist: torch (>=2.0.1,<3.0.0)
Requires-Dist: torchmetrics (>=1.1.2,<2.0.0)
